hanzi2reading/__init__.py
hanzi2reading/create_db.py
hanzi2reading/create_moedict.py
hanzi2reading/pinyin.py
hanzi2reading/read.py
hanzi2reading/read_db.py
hanzi2reading/reading.py
hanzi2reading/serialize.py
hanzi2reading/syllable.py
hanzi2reading/trie.py
hanzi2reading/zhuyin.py
hanzi2reading/data/moedict.h2r
hanzi2reading/data/pinyin.txt
hanzi2reading-0.1.1.data/scripts/hanzi2reading
test/__init__.py
test/test_read.py
test/test_serialize.py
test/test_syllable.py
hanzi2reading-0.1.1.dist-info/METADATA
hanzi2reading-0.1.1.dist-info/WHEEL
hanzi2reading-0.1.1.dist-info/top_level.txt
hanzi2reading-0.1.1.dist-info/RECORD
